{
  "db_name": "PostgreSQL",
  "query": "\n        SELECT pp.user_id\n        FROM player_pool pp\n        INNER JOIN users u ON pp.user_id = u.id\n        WHERE pp.user_id = $1 AND u.status = 'active'\n        ",
  "describe": {
    "columns": [
      {
        "ordinal": 0,
        "name": "user_id",
        "type_info": "Uuid"
      }
    ],
    "parameters": {
      "Left": [
        "Uuid"
      ]
    },
    "nullable": [
      false
    ]
  },
  "hash": "7ed675a3955d0deb1ec3632cf7caabb794a39cb2d5e4618483acfcb378174a46"
}
