{
  "db_name": "PostgreSQL",
  "query": "\n                    UPDATE workout_data \n                    SET heart_rate_zones = $1,\n                        stamina_gained = $2,\n                        strength_gained = $3,\n                        total_points_gained = $4\n                    WHERE id = $5\n                    ",
  "describe": {
    "columns": [],
    "parameters": {
      "Left": [
        "Jsonb",
        "Int4",
        "Int4",
        "Int4",
        "Uuid"
      ]
    },
    "nullable": []
  },
  "hash": "31e5b7bfba5bed846a08b1499847ee666e24c9df282e97aeebd95b195438ca62"
}
