{
  "db_name": "PostgreSQL",
  "query": "\n        UPDATE users\n        SET status = $1, updated_at = $2\n        WHERE id = $3\n        RETURNING status as \"status: UserStatus\"\n        ",
  "describe": {
    "columns": [
      {
        "ordinal": 0,
        "name": "status: UserStatus",
        "type_info": "Varchar"
      }
    ],
    "parameters": {
      "Left": [
        "Varchar",
        "Timestamptz",
        "Uuid"
      ]
    },
    "nullable": [
      false
    ]
  },
  "hash": "e9753c71a37a05da4c355034ea4e087dbfe4824eab4cccda861bae7f5994cbb2"
}
